pvue/__init__.py
pvue/cli.py
pvue/eel.py
pvue/logger.py
pvue/main.py
pvue/webview.py
pvue/backend/__init__.py
pvue/backend/server.py
pvue/static/app.js
pvue/static/index.html
pvue/static/style.css
pvue/utils/__init__.py
pvue-0.4.0.dist-info/licenses/LICENSE.txt
pvue-0.4.0.dist-info/METADATA
pvue-0.4.0.dist-info/WHEEL
pvue-0.4.0.dist-info/entry_points.txt
pvue-0.4.0.dist-info/top_level.txt
pvue-0.4.0.dist-info/RECORD
