Metadata-Version: 2.4
Name: pvue
Version: 0.4.0
Summary: A Python framework that integrates Vue 3 frontend with Python backend using WebSocket
Home-page: https://github.com/yourusername/pvue
Author: Your Name
Author-email: your.email@example.com
License: MIT
Keywords: vue,python,websocket,desktop,gui,python3.14
Classifier: Development Status :: 3 - Alpha
Classifier: Intended Audience :: Developers
Classifier: Topic :: Software Development :: Libraries :: Python Modules
Classifier: License :: OSI Approved :: MIT License
Classifier: Programming Language :: Python :: 3.6
Classifier: Programming Language :: Python :: 3.7
Classifier: Programming Language :: Python :: 3.8
Classifier: Programming Language :: Python :: 3.9
Classifier: Programming Language :: Python :: 3.10
Classifier: Programming Language :: Python :: 3.11
Classifier: Programming Language :: Python :: 3.12
Classifier: Programming Language :: Python :: 3.13
Classifier: Programming Language :: Python :: 3.14
Classifier: Programming Language :: Python :: Implementation :: CPython
Classifier: Programming Language :: Python :: Implementation :: PyPy
Requires-Python: >=3.6
License-File: LICENSE.txt
Requires-Dist: websockets>=9.1
Requires-Dist: eel>=0.17.0
Requires-Dist: proxy_tools>=0.1.0
Requires-Dist: typing_extensions>=3.7.4.3; python_version <= "3.7"
Provides-Extra: webview
Requires-Dist: pywebview>=6.1; extra == "webview"
Provides-Extra: full
Requires-Dist: pywebview>=6.1; extra == "full"
Dynamic: author
Dynamic: author-email
Dynamic: classifier
Dynamic: description
Dynamic: description-content-type
Dynamic: home-page
Dynamic: keywords
Dynamic: license
Dynamic: license-file
Dynamic: provides-extra
Dynamic: requires-dist
Dynamic: requires-python
Dynamic: summary
